osilic/__init__.py
osilic/model.py
osilic-0.2.2.dist-info/METADATA
osilic-0.2.2.dist-info/WHEEL
osilic-0.2.2.dist-info/entry_points.txt
osilic-0.2.2.dist-info/licenses/LICENSE
osilic-0.2.2.dist-info/RECORD
