Metadata-Version: 2.4
Name: osilic
Version: 0.2.2
Summary: An utility for listing & searching Open Source Initiative licenses via their public API
Author-email: Dinesh <dineshr93@gmail.com>
License-File: LICENSE
Requires-Python: >=3.10
Requires-Dist: tabulate>=0.9.0
